odoo/addons/l10n_es_mis_report/README.rst
odoo/addons/l10n_es_mis_report/__init__.py
odoo/addons/l10n_es_mis_report/__manifest__.py
odoo/addons/l10n_es_mis_report/data/mis_report_balance_abreviated.xml
odoo/addons/l10n_es_mis_report/data/mis_report_balance_normal.xml
odoo/addons/l10n_es_mis_report/data/mis_report_balance_sme.xml
odoo/addons/l10n_es_mis_report/data/mis_report_balance_sme_sfl.xml
odoo/addons/l10n_es_mis_report/data/mis_report_pyg_abreviated.xml
odoo/addons/l10n_es_mis_report/data/mis_report_pyg_normal.xml
odoo/addons/l10n_es_mis_report/data/mis_report_pyg_sme.xml
odoo/addons/l10n_es_mis_report/data/mis_report_pyg_sme_sfl.xml
odoo/addons/l10n_es_mis_report/data/mis_report_revenues_expenses_normal.xml
odoo/addons/l10n_es_mis_report/data/mis_report_styles.xml
odoo/addons/l10n_es_mis_report/i18n/ca.po
odoo/addons/l10n_es_mis_report/i18n/es.po
odoo/addons/l10n_es_mis_report/i18n/l10n_es_mis_report.pot
odoo/addons/l10n_es_mis_report/readme/CONTRIBUTORS.md
odoo/addons/l10n_es_mis_report/readme/DESCRIPTION.md
odoo/addons/l10n_es_mis_report/readme/INSTALL.md
odoo/addons/l10n_es_mis_report/readme/USAGE.md
odoo/addons/l10n_es_mis_report/static/description/icon.png
odoo/addons/l10n_es_mis_report/static/description/index.html
odoo_addon_l10n_es_mis_report-18.0.1.0.0.2.dist-info/METADATA
odoo_addon_l10n_es_mis_report-18.0.1.0.0.2.dist-info/WHEEL
odoo_addon_l10n_es_mis_report-18.0.1.0.0.2.dist-info/top_level.txt
odoo_addon_l10n_es_mis_report-18.0.1.0.0.2.dist-info/RECORD
