Metadata-Version: 2.1
Name: odoo-addon-l10n_es_mis_report
Version: 18.0.1.0.0.2
Requires-Python: >=3.10
Requires-Dist: odoo-addon-mis_builder==18.0.*
Requires-Dist: odoo==18.0.*
Summary: =?utf-8?q?Plantillas_MIS_Builder_para_informes_contables_espa=C3=B1oles?=
Home-page: https://github.com/OCA/l10n-spain
License: AGPL-3
Author: ForgeFlow, Tecnativa, Odoo Community Association (OCA)
Author-email: support@odoo-community.org
Classifier: Programming Language :: Python
Classifier: Framework :: Odoo
Classifier: Framework :: Odoo :: 18.0
Classifier: License :: OSI Approved :: GNU Affero General Public License v3
